setup.py
protected/__init__.py
protected/string.py
protected.egg-info/PKG-INFO
protected.egg-info/SOURCES.txt
protected.egg-info/dependency_links.txt
protected.egg-info/top_level.txt
protected.egg-info/zip-safe