Metadata-Version: 1.0
Name: protected
Version: 0.0.1
Summary: "Proteted" data types suitable for hiding secrets in Django config files.
Home-page: https://github.com/wnyc/protected
Author: Adam DePrince
Author-email: adeprince@nypublicradio.org
License: MIT
Platform: UNKNOWN
